CHANGES.rst
DOCS-LICENSE
LICENSE
LICENSE-MIT
MANIFEST.in
README.rst
setup.py
tomcom/__init__.py
tomcom.plone.bootstrap.egg-info/PKG-INFO
tomcom.plone.bootstrap.egg-info/SOURCES.txt
tomcom.plone.bootstrap.egg-info/dependency_links.txt
tomcom.plone.bootstrap.egg-info/entry_points.txt
tomcom.plone.bootstrap.egg-info/namespace_packages.txt
tomcom.plone.bootstrap.egg-info/not-zip-safe
tomcom.plone.bootstrap.egg-info/requires.txt
tomcom.plone.bootstrap.egg-info/top_level.txt
tomcom/plone/__init__.py
tomcom/plone/bootstrap/__init__.py
tomcom/plone/bootstrap/configure.zcml
tomcom/plone/bootstrap/profiles.zcml
tomcom/plone/bootstrap/profiles/default/cssregistry.xml
tomcom/plone/bootstrap/profiles/default/jsregistry.xml
tomcom/plone/bootstrap/resource/css/bootstrap-theme.css
tomcom/plone/bootstrap/resource/css/bootstrap-theme.min.css
tomcom/plone/bootstrap/resource/css/bootstrap.css
tomcom/plone/bootstrap/resource/css/bootstrap.min.css
tomcom/plone/bootstrap/resource/fonts/glyphicons-halflings-regular.eot
tomcom/plone/bootstrap/resource/fonts/glyphicons-halflings-regular.svg
tomcom/plone/bootstrap/resource/fonts/glyphicons-halflings-regular.ttf
tomcom/plone/bootstrap/resource/fonts/glyphicons-halflings-regular.woff
tomcom/plone/bootstrap/resource/js/bootstrap.js
tomcom/plone/bootstrap/resource/js/bootstrap.min.js