Metadata-Version: 1.1
Name: tomcom.plone.bootstrap
Version: 3.0.2
Summary: bootstrap for plone
Home-page: https://github.com/tomcom-de/tomcom.plone.bootstrap
Author: tomcom GmbH
Author-email: mailto:info@tomcom.de
License: GPL
Keywords: font awesome
Platform: UNKNOWN
Classifier: Framework :: Plone
Classifier: Framework :: Plone :: 4.3
Classifier: Programming Language :: Python
Classifier: Topic :: Software Development :: Libraries :: Python Modules
